NDimInv/ND_Data.py
NDimInv/ND_Model.py
NDimInv/__init__.py
NDimInv/data_weighting.py
NDimInv/elem.py
NDimInv/helper.py
NDimInv/main.py
NDimInv/model_template.py
NDimInv/plot_helper.py
NDimInv/reg_pars.py
NDimInv/regs.py
NDimInv/version.py
sip_formats/__init__.py
sip_formats/convert.py
sip_formats/test_convert.py
geccoinv-0.8.6.dist-info/COPYING
geccoinv-0.8.6.dist-info/LICENCE
geccoinv-0.8.6.dist-info/METADATA
geccoinv-0.8.6.dist-info/WHEEL
geccoinv-0.8.6.dist-info/top_level.txt
geccoinv-0.8.6.dist-info/RECORD
