Metadata-Version: 2.1
Name: geccoinv
Version: 0.8.6
Summary: Multi dimensional geophysical inversion framework. Note: only for use with the ccd package. If you are looking for a general inversion framework, try pyGimli (www.pygimli.org)
Home-page: http://www.geo.uni-bonn.de
Author: Maximilian Weigand
Author-email: mweigand@geo.uni-bonn.de
License: UNKNOWN
Platform: UNKNOWN
Requires-Dist: numpy
Requires-Dist: scipy (>=0.12)
Requires-Dist: matplotlib
